{"type": "FeatureCollection", "features": [{"geometry": {"type": "Point", "coordinates": [-1.2212730459027754, 51.764126177757745]}, "type": "Feature", "properties": {"destination": "Cowley & City", "service": "10", "approaching": {"name": "JRH West Wing Stop J7", "area": "Headington"}}}, {"geometry": {"type": "Point", "coordinates": [-1.1999689049517512, 51.751861520424775]}, "type": "Feature", "properties": {"destination": "Cowley & City", "service": "10", "approaching": {"name": "Community Centre", "area": "Wood Farm"}}}, {"geometry": {"type": "Point", "coordinates": [-1.2057850038860691, 51.737459331137522]}, "type": "Feature", "properties": {"destination": "City Centre", "service": "10", "approaching": {"name": "Crescent Hall", "area": "Cowley"}}}, {"geometry": {"type": "Point", "coordinates": [-1.2151202919978306, 51.735336916035195]}, "type": "Feature", "properties": {"destination": "City Centre", "service": "10", "approaching": {"name": "Clive Road", "area": "Cowley"}}}]}