{"type": "FeatureCollection", "features": [{"geometry": {"type": "Point", "coordinates": [-1.5081042891077059, 51.779784978239135]}, "type": "Feature", "properties": {"destination": "Oxford", "service": "S1", "approaching": {"name": "Thorney Leys", "area": "Witney"}}}, {"geometry": {"type": "Point", "coordinates": [-1.5081042891077059, 51.779784978239135]}, "type": "Feature", "properties": {"destination": "Oxford", "service": "S1", "approaching": {"name": "Thorney Leys", "area": "Witney"}}}, {"geometry": {"type": "Point", "coordinates": [-1.4953614510515756, 51.778481068714825]}, "type": "Feature", "properties": {"destination": "Oxford", "service": "S1", "approaching": {"name": "Burwell Shops", "area": "Witney"}}}, {"geometry": {"type": "Point", "coordinates": [-1.3105673097551174, 51.749325059822333]}, "type": "Feature", "properties": {"destination": "City Centre", "service": "S1", "approaching": {"name": "Grange Court", "area": "Botley"}}}, {"geometry": {"type": "Point", "coordinates": [-1.3011839970877181, 51.749971041924987]}, "type": "Feature", "properties": {"destination": "City Centre", "service": "S1", "approaching": {"name": "Tilbury Lane", "area": "Botley"}}}]}